better_timetagger_cli/__init__.py
better_timetagger_cli/__main__.py
better_timetagger_cli/py.typed
better_timetagger_cli/cli/__init__.py
better_timetagger_cli/cli/_cli.py
better_timetagger_cli/cli/app_cmd.py
better_timetagger_cli/cli/diagnose_cmd.py
better_timetagger_cli/cli/export_cmd.py
better_timetagger_cli/cli/import_cmd.py
better_timetagger_cli/cli/remove_cmd.py
better_timetagger_cli/cli/restore_cmd.py
better_timetagger_cli/cli/resume_cmd.py
better_timetagger_cli/cli/setup_cmd.py
better_timetagger_cli/cli/show_cmd.py
better_timetagger_cli/cli/start_cmd.py
better_timetagger_cli/cli/status_cmd.py
better_timetagger_cli/cli/stop_cmd.py
better_timetagger_cli/lib/__init__.py
better_timetagger_cli/lib/api.py
better_timetagger_cli/lib/cli.py
better_timetagger_cli/lib/config.py
better_timetagger_cli/lib/csv.py
better_timetagger_cli/lib/output.py
better_timetagger_cli/lib/parsing.py
better_timetagger_cli/lib/records.py
better_timetagger_cli/lib/timestamps.py
better_timetagger_cli/lib/types.py
better_timetagger_cli-0.6.1.dist-info/METADATA
better_timetagger_cli-0.6.1.dist-info/WHEEL
better_timetagger_cli-0.6.1.dist-info/entry_points.txt
better_timetagger_cli-0.6.1.dist-info/licenses/LICENSE
better_timetagger_cli-0.6.1.dist-info/RECORD
