Metadata-Version: 2.4
Name: better-timetagger-cli
Version: 0.6.1
Summary: A command line tool for TimeTagger. This is a more feature-rich and ergonomic fork of the original timetagger-cli (by Almar Klein), providing better user experience and additional features.
Project-URL: Documentation, https://better-timetagger-cli.readthedocs.io
Project-URL: Repository, https://github.com/PassionateBytes/better-timetagger-cli
Project-URL: Issues, https://github.com/PassionateBytes/better-timetagger-cli/issues
Author-email: Paul Bütof <paul@passionate-bytes.com>
Maintainer-email: Paul Bütof <paul@passionate-bytes.com>
License-File: LICENSE
Keywords: cli,command-line,productivity,self-hosted,self-hosting,time,time-tracking,timetagger,tracking
Requires-Python: >=3.10
Requires-Dist: click>=8.2.0
Requires-Dist: parsedatetime>=2.6
Requires-Dist: platformdirs>=4.3.8
Requires-Dist: requests>=2.32.3
Requires-Dist: rich>=14.0.0
Requires-Dist: tomlkit>=0.13.2
